LICENSE
MANIFEST.in
README.md
README.rst
setup.cfg
setup.py
bemo/__init__.py
bemo/functional.py
bemo/handlers.py
bemo/sessions.py
bemo/templates.py
bemo.egg-info/PKG-INFO
bemo.egg-info/SOURCES.txt
bemo.egg-info/dependency_links.txt
bemo.egg-info/not-zip-safe
bemo.egg-info/requires.txt
bemo.egg-info/top_level.txt
bemo/templates/asserts/call_count.jinja2
bemo/templates/asserts/calls.jinja2
bemo/templates/xhook/enable.jinja2
bemo/templates/xhook/handlers.jinja2
bemo/templates/xhook/initialize.jinja2
bemo/templates/xhook/release.jinja2