Metadata-Version: 1.1
Name: bemo
Version: 0.0.2
Summary: It's simple way to mock your back-end from webdriver UI tests
Home-page: https://github.com/bemo-project/bemo-python
Author: Nikita Grishko
Author-email: gr1n@protonmail.com
License: MIT
Download-URL: https://pypi.python.org/pypi/bemo/
Platform: UNKNOWN
Classifier: Development Status :: 2 - Pre-Alpha
Classifier: Environment :: Web Environment
Classifier: Intended Audience :: Developers
Classifier: License :: OSI Approved :: MIT License
Classifier: Operating System :: OS Independent
Classifier: Programming Language :: Python
Classifier: Programming Language :: Python :: 2
Classifier: Programming Language :: Python :: 2.7
Classifier: Programming Language :: Python :: 3
Classifier: Programming Language :: Python :: 3.5
Classifier: Topic :: Software Development :: Libraries :: Python Modules
